mb_cruise_migration/clean_cruise.py
mb_cruise_migration/cleaner.py
mb_cruise_migration/migration_properties.py
mb_cruise_migration/migrator.py
mb_cruise_migration/start_migration.py
mb_cruise_migration/db/cruise_connection.py
mb_cruise_migration/db/cruise_db.py
mb_cruise_migration/db/mb_db.py
mb_cruise_migration/db/oracledb_pooled.py
mb_cruise_migration/db/query_builder.py
mb_cruise_migration/framework/cache.py
mb_cruise_migration/framework/file_decoder.py
mb_cruise_migration/framework/file_filter.py
mb_cruise_migration/framework/file_labeler.py
mb_cruise_migration/framework/file_validator.py
mb_cruise_migration/framework/paginator.py
mb_cruise_migration/framework/parsed_data_file.py
mb_cruise_migration/framework/survey_filter.py
mb_cruise_migration/framework/thread_safe_mappings.py
mb_cruise_migration/framework/consts/const_initializer.py
mb_cruise_migration/framework/consts/data_file_consts.py
mb_cruise_migration/framework/consts/data_file_part_consts.py
mb_cruise_migration/framework/consts/dataset_type_consts.py
mb_cruise_migration/framework/consts/date_consts.py
mb_cruise_migration/framework/consts/error_consts.py
mb_cruise_migration/framework/consts/file_format_consts.py
mb_cruise_migration/framework/consts/file_label_consts.py
mb_cruise_migration/framework/consts/file_type_consts.py
mb_cruise_migration/framework/consts/instrument_consts.py
mb_cruise_migration/framework/consts/log_level_consts.py
mb_cruise_migration/framework/consts/nos_hydro_surveys.py
mb_cruise_migration/framework/consts/parameter_detail_consts.py
mb_cruise_migration/framework/consts/platform_type_consts.py
mb_cruise_migration/framework/consts/survey_blacklist.py
mb_cruise_migration/framework/consts/version_consts.py
mb_cruise_migration/framework/consts/version_description_consts.py
mb_cruise_migration/framework/resolvers/dataset_type_resolver.py
mb_cruise_migration/framework/resolvers/file_format_resolver.py
mb_cruise_migration/framework/resolvers/file_type_resolver.py
ci_cmg_mb_cruise_migration-1.28.6.dist-info/METADATA
ci_cmg_mb_cruise_migration-1.28.6.dist-info/WHEEL
ci_cmg_mb_cruise_migration-1.28.6.dist-info/licenses/LICENSE
ci_cmg_mb_cruise_migration-1.28.6.dist-info/RECORD
