Metadata-Version: 2.4
Name: ci-cmg-mb-cruise-migration
Version: 1.28.6
Dynamic: Requires-Dist
Summary: migrates multibeam metadata from mb schema to cruise schema
Project-URL: Github, https://github.com/CI-CMG/mb-cruise-migration
License-File: LICENSE
Classifier: License :: OSI Approved :: MIT License
Classifier: Operating System :: OS Independent
Classifier: Programming Language :: Python :: 3
Requires-Python: >=3.10
